dsis_model_sdk/__init__.py
dsis_model_sdk/exceptions.py
dsis_model_sdk/py.typed
dsis_model_sdk/examples/basic_usage.py
dsis_model_sdk/models/__init__.py
dsis_model_sdk/models/common/__init__.py
dsis_model_sdk/models/common/application_data.py
dsis_model_sdk/models/common/application_data2.py
dsis_model_sdk/models/common/base.py
dsis_model_sdk/models/common/basin.py
dsis_model_sdk/models/common/binset_grid_3d_grid.py
dsis_model_sdk/models/common/carto_reference_system.py
dsis_model_sdk/models/common/casing.py
dsis_model_sdk/models/common/company.py
dsis_model_sdk/models/common/computed_lithology.py
dsis_model_sdk/models/common/computed_lithology_header.py
dsis_model_sdk/models/common/concept_plans.py
dsis_model_sdk/models/common/concept_site_outlines.py
dsis_model_sdk/models/common/concept_sites.py
dsis_model_sdk/models/common/concept_targets.py
dsis_model_sdk/models/common/concepts.py
dsis_model_sdk/models/common/contour_line.py
dsis_model_sdk/models/common/contour_parameter.py
dsis_model_sdk/models/common/contour_set.py
dsis_model_sdk/models/common/control_point.py
dsis_model_sdk/models/common/data_dictionary.py
dsis_model_sdk/models/common/data_dictionary_value.py
dsis_model_sdk/models/common/data_source.py
dsis_model_sdk/models/common/data_source_user_permission.py
dsis_model_sdk/models/common/dipmeter.py
dsis_model_sdk/models/common/directional_survey.py
dsis_model_sdk/models/common/drillers_estimator_point.py
dsis_model_sdk/models/common/editor_templates.py
dsis_model_sdk/models/common/em_contour.py
dsis_model_sdk/models/common/em_structural_body.py
dsis_model_sdk/models/common/em_structural_model.py
dsis_model_sdk/models/common/fault.py
dsis_model_sdk/models/common/fault_center_line.py
dsis_model_sdk/models/common/fault_center_line_set.py
dsis_model_sdk/models/common/fault_display.py
dsis_model_sdk/models/common/fault_grid.py
dsis_model_sdk/models/common/fault_list.py
dsis_model_sdk/models/common/fault_list_member.py
dsis_schemas-0.0.2.dist-info/METADATA
dsis_schemas-0.0.2.dist-info/WHEEL
dsis_schemas-0.0.2.dist-info/entry_points.txt
dsis_schemas-0.0.2.dist-info/top_level.txt
dsis_schemas-0.0.2.dist-info/RECORD
