Metadata-Version: 2.4
Name: dsis-schemas
Version: 0.0.2
Summary: Python SDK for DSIS OpenWorks Common Model and OW5000 Native Model schemas
Author-email: DSIS Team <dsis@equinor.com>
Maintainer-email: DSIS Team <dsis@equinor.com>
License: MIT
Project-URL: Homepage, https://github.com/equinor/dsis-schemas
Project-URL: Documentation, https://github.com/equinor/dsis-schemas/blob/main/README.md
Project-URL: Repository, https://github.com/equinor/dsis-schemas
Project-URL: Issues, https://github.com/equinor/dsis-schemas/issues
Keywords: openworks,dsis,schemas,oil,gas,geology,seismic
Classifier: Development Status :: 4 - Beta
Classifier: Intended Audience :: Developers
Classifier: Intended Audience :: Science/Research
Classifier: License :: OSI Approved :: MIT License
Classifier: Operating System :: OS Independent
Classifier: Programming Language :: Python :: 3
Classifier: Programming Language :: Python :: 3.8
Classifier: Programming Language :: Python :: 3.9
Classifier: Programming Language :: Python :: 3.10
Classifier: Programming Language :: Python :: 3.11
Classifier: Programming Language :: Python :: 3.12
Classifier: Topic :: Scientific/Engineering
Classifier: Topic :: Software Development :: Libraries :: Python Modules
Requires-Python: >=3.8
Requires-Dist: pydantic<3.0.0,>=2.0.0
Requires-Dist: typing-extensions>=4.0.0
Provides-Extra: dev
Requires-Dist: pytest>=7.0.0; extra == "dev"
Requires-Dist: pytest-cov>=4.0.0; extra == "dev"
Requires-Dist: black>=23.0.0; extra == "dev"
Requires-Dist: isort>=5.12.0; extra == "dev"
Requires-Dist: flake8>=6.0.0; extra == "dev"
Requires-Dist: mypy>=1.0.0; extra == "dev"
Requires-Dist: pre-commit>=3.0.0; extra == "dev"
Provides-Extra: docs
Requires-Dist: sphinx>=6.0.0; extra == "docs"
Requires-Dist: sphinx-rtd-theme>=1.2.0; extra == "docs"
Requires-Dist: sphinx-autodoc-typehints>=1.20.0; extra == "docs"
Provides-Extra: integration
Requires-Dist: jaydebeapi>=1.2.3; extra == "integration"
Requires-Dist: requests>=2.28.0; extra == "integration"
